browsergym/core/__init__.py
browsergym/core/chat.py
browsergym/core/constants.py
browsergym/core/env.py
browsergym/core/observation.py
browsergym/core/registration.py
browsergym/core/spaces.py
browsergym/core/task.py
browsergym/core/action/__init__.py
browsergym/core/action/base.py
browsergym/core/action/functions.py
browsergym/core/action/highlevel.py
browsergym/core/action/parsers.py
browsergym/core/action/python.py
browsergym/core/action/utils.py
browsergym/core/chat_files/assistant.png
browsergym/core/chat_files/chatbox.html
browsergym/core/chat_files/chatbox_modern.html
browsergym/core/chat_files/img/send.svg
browsergym/core/javascript/frame_mark_elements.js
browsergym/core/javascript/frame_unmark_elements.js
browsergym/utils/mcp_server.py
browsergym/utils/obs.py
browsergym_core-0.14.3.dist-info/METADATA
browsergym_core-0.14.3.dist-info/WHEEL
browsergym_core-0.14.3.dist-info/RECORD
