Metadata-Version: 2.4
Name: browsergym-core
Version: 0.14.3
Summary: BrowserGym: a gym environment for web task automation in the Chromium browser
Project-URL: homepage, https://github.com/ServiceNow/BrowserGym
Author: Rim Assouel, Léo Boisvert, Massimo Caccia, Alex Drouin, Maxime Gasse, Imene Kerboua, Alex Lacoste, Thibault Le Sellier De Chezelles, Tom Marty
License: Apache-2.0
Classifier: Development Status :: 3 - Alpha
Classifier: Intended Audience :: Science/Research
Classifier: License :: OSI Approved :: Apache Software License
Classifier: Operating System :: OS Independent
Classifier: Programming Language :: Python :: 3
Classifier: Topic :: Scientific/Engineering :: Artificial Intelligence
Requires-Python: >3.9
Requires-Dist: beautifulsoup4>=4.12
Requires-Dist: gymnasium>=0.27
Requires-Dist: lxml<6.0.0,>=4.9
Requires-Dist: mcp[cli]>=1.6.0
Requires-Dist: numpy>=1.14
Requires-Dist: pillow>=10.1
Requires-Dist: playwright==1.44
Requires-Dist: pyparsing>=3
